jira2py/__init__.py
jira2py/issue_comments.py
jira2py/issue_fields.py
jira2py/issue_search.py
jira2py/issues.py
jira2py/jira_base.py
jira2py-0.3.1.dist-info/licenses/LICENSE
jira2py-0.3.1.dist-info/METADATA
jira2py-0.3.1.dist-info/WHEEL
jira2py-0.3.1.dist-info/top_level.txt
jira2py-0.3.1.dist-info/RECORD
