Metadata-Version: 2.4
Name: jira2py
Version: 0.3.1
Summary: The Python library to interact with Atlassian Jira REST API
Author-email: nEver1 <7fhhwpuuo@mozmail.com>
License-Expression: MIT
Project-URL: Homepage, https://github.com/en-ver/jira2py
Project-URL: Repository, https://github.com/en-ver/jira2py
Classifier: Programming Language :: Python :: 3
Classifier: Operating System :: OS Independent
Requires-Python: >=3.11
License-File: LICENSE
Requires-Dist: email-validator==2.2.0
Requires-Dist: pydantic==2.11.4
Requires-Dist: pydantic-core==2.33.2
Requires-Dist: python-dotenv==1.1.0
Requires-Dist: requests==2.32.3
Provides-Extra: deployment
Requires-Dist: setuptools>=42; extra == "deployment"
Requires-Dist: wheel; extra == "deployment"
Requires-Dist: twine; extra == "deployment"
Requires-Dist: build; extra == "deployment"
Provides-Extra: dev
Requires-Dist: ipykernel; extra == "dev"
Dynamic: license-file
